django_multiple_form_view-0.1.0.dist-info/DESCRIPTION.rst
django_multiple_form_view-0.1.0.dist-info/METADATA
django_multiple_form_view-0.1.0.dist-info/RECORD
django_multiple_form_view-0.1.0.dist-info/WHEEL
django_multiple_form_view-0.1.0.dist-info/metadata.json
django_multiple_form_view-0.1.0.dist-info/top_level.txt
multiple_form_view/__init__.py
